patch_path/__init__.py
patch_path/main.py
patch_path-1.0.0.dist-info/METADATA
patch_path-1.0.0.dist-info/WHEEL
patch_path-1.0.0.dist-info/entry_points.txt
patch_path-1.0.0.dist-info/RECORD
