Metadata-Version: 2.4
Name: patch-path
Version: 1.0.0
Summary: Run a command with patched executables on the path
Project-URL: Homepage, https://github.com/yourusername/patch-path
Project-URL: Repository, https://github.com/yourusername/patch-path
Project-URL: Issues, https://github.com/yourusername/patch-path/issues
Author-email: "@readwithai" <talwrii@gmail.com>
License: MIT
Classifier: Development Status :: 3 - Alpha
Classifier: Intended Audience :: Developers
Classifier: License :: OSI Approved :: MIT License
Classifier: Programming Language :: Python :: 3
Classifier: Programming Language :: Python :: 3.7
Classifier: Programming Language :: Python :: 3.8
Classifier: Programming Language :: Python :: 3.9
Classifier: Programming Language :: Python :: 3.10
Classifier: Programming Language :: Python :: 3.11
Classifier: Programming Language :: Python :: 3.12
Requires-Python: >=3.7
